squirrelbattle/__init__.py
squirrelbattle/bootstrap.py
squirrelbattle/enums.py
squirrelbattle/game.py
squirrelbattle/interfaces.py
squirrelbattle/menus.py
squirrelbattle/resources.py
squirrelbattle/settings.py
squirrelbattle/term_manager.py
squirrelbattle/translations.py
squirrelbattle/assets/ascii-art-ecureuil.txt
squirrelbattle/assets/ascii_art-title.txt
squirrelbattle/assets/example_map.txt
squirrelbattle/assets/example_map_2.txt
squirrelbattle/assets/example_map_3.txt
squirrelbattle/display/__init__.py
squirrelbattle/display/display.py
squirrelbattle/display/display_manager.py
squirrelbattle/display/gamedisplay.py
squirrelbattle/display/menudisplay.py
squirrelbattle/display/texturepack.py
squirrelbattle/entities/__init__.py
squirrelbattle/entities/friendly.py
squirrelbattle/entities/items.py
squirrelbattle/entities/monsters.py
squirrelbattle/entities/player.py
squirrelbattle/locale/de/LC_MESSAGES/squirrelbattle.mo
squirrelbattle/locale/es/LC_MESSAGES/squirrelbattle.mo
squirrelbattle/locale/fr/LC_MESSAGES/squirrelbattle.mo
squirrelbattle/mapgeneration/__init__.py
squirrelbattle/mapgeneration/broguelike.py
squirrelbattle/tests/__init__.py
squirrelbattle/tests/entities_test.py
squirrelbattle/tests/game_test.py
squirrelbattle/tests/interfaces_test.py
squirrelbattle/tests/mapgeneration_test.py
squirrelbattle/tests/screen.py
squirrelbattle/tests/settings_test.py
squirrelbattle/tests/translations_test.py
squirrel_battle-23.14.dist-info/COPYING
squirrel_battle-23.14.dist-info/METADATA
squirrel_battle-23.14.dist-info/WHEEL
squirrel_battle-23.14.dist-info/entry_points.txt
squirrel_battle-23.14.dist-info/top_level.txt
squirrel_battle-23.14.dist-info/RECORD
