Metadata-Version: 2.1
Name: squirrel-battle
Version: 23.14
Summary: Watch out for squirrel's knives!
Home-page: https://gitlab.crans.org/ynerant/squirrel-battle
Author: ÿnérant, eichhornchen, nicomarg, charlse
Author-email: squirrel-battle@crans.org
License: GPLv3
Platform: UNKNOWN
Classifier: Development Status :: 4 - Beta
Classifier: Environment :: Console :: Curses
Classifier: License :: OSI Approved :: GNU General Public License v3 (GPLv3)
Classifier: Natural Language :: French
Classifier: Operating System :: OS Independent
Classifier: Programming Language :: Python :: 3
Classifier: Programming Language :: Python :: 3.6
Classifier: Programming Language :: Python :: 3.7
Classifier: Programming Language :: Python :: 3.8
Classifier: Programming Language :: Python :: 3.9
Classifier: Topic :: Games/Entertainment
Requires-Python: >=3.6
